json_file/json_file.py
json_file/manifest.toml
opsbox_json_file_output-0.1.1.dist-info/LICENCE.txt
opsbox_json_file_output-0.1.1.dist-info/METADATA
opsbox_json_file_output-0.1.1.dist-info/WHEEL
opsbox_json_file_output-0.1.1.dist-info/entry_points.txt
opsbox_json_file_output-0.1.1.dist-info/top_level.txt
opsbox_json_file_output-0.1.1.dist-info/RECORD
